4to1multiplexer/Behavioural/mult.v
module mux( select, d, q );

input[1:0] select;
input[3:0] d;
output     q;

wire      q;
wire[1:0] select;
wire[3:0] d;

assign q = d[select];

endmodule

4to1multiplexer/Behavioural/mux_tb.v
`timescale 1ns/100ps
`include "mult.v"

module Top;

reg[3:0] in;
reg[1:0] sel;
wire q;

mux mux1(sel,in,q);

initial 

begin
	$dumpfile("mux.vcd");
	$dumpvars;

	$monitor($time,"sel=%b, d=%b, q=%b\n",sel,in,q);
	sel=2'b10;in=4'b1000;
	#5 sel=2'b10;in=4'b1010;
	#5 sel=2'b10;in=4'b1000;
	#5 sel=2'b10;in=4'b1011;
	#5 sel=2'b10;in=4'b1111;
	#5 sel=2'b10;in=4'b0010;
	#5 sel=2'b10;in=4'b0100;
	#5 sel=2'b10;in=4'b1110;
	#5 sel=2'b10;in=4'b0011;
	#5;



end

endmodule

4to1multiplexer/Behavioural/mux.vcd
$date
	Sun Oct  1 18:26:53 2017
$end
$version
	Icarus Verilog
$end
$timescale
	100ps
$end
$scope module Top $end
$var wire 1 ! q $end
$var reg 4 " in [3:0] $end
$var reg 2 # sel [1:0] $end
$scope module mux1 $end
$var wire 4 $ d [3:0] $end
$var wire 2 % select [1:0] $end
$var wire 1 ! q $end
$upscope $end
$upscope $end
$enddefinitions $end
#0
$dumpvars
b10 %
b1000 $
b10 #
b1000 "
0!
$end
#50
b1010 "
b1010 $
#100
b1000 "
b1000 $
#150
b1011 "
b1011 $
#200
1!
b1111 "
b1111 $
#250
0!
b10 "
b10 $
#300
1!
b100 "
b100 $
#350
b1110 "
b1110 $
#400
0!
b11 "
b11 $
