4_Bit_Binary_Counter/counter.v
module counter(clk,reset,Q);

input clk;
output[3:0] Q;
input reset;

wire clk,reset;
reg[3:0] Q;


initial Q=0;

always @ (posedge(clk)) 
	begin
		if (reset)
		
			Q<=0;
		
		else 
		
			
			Q <=Q+1;
			
			
	end
endmodule

4_Bit_Binary_Counter/Behavioural model/counter_tb.v
`timescale 1ns/100ps
`include "counter.v"

module Top;
reg clk;
reg reset;
wire[3:0] Q;

counter c1(clk, reset , Q);
 

initial 
	begin
		reset = 0;
		#1000 reset=1;
		#100 reset=0;
		#5000 reset=1;
		#100  reset=0;
		#10000 $finish;

	end

always 
	begin

		clk = 0; #50;
		clk = 1; #50;
	end

initial
begin
	

 $monitor($stime," clk = %b, reset = %b, dout = %h",clk,reset,Q );
$dumpfile("counter.vcd");
$dumpvars;

end
endmodule

4_Bit_Binary_Counter/Behavioural model/counter.vcd
$date
	Thu Oct 12 16:39:41 2017
$end
$version
	Icarus Verilog
$end
$timescale
	100ps
$end
$scope module Top $end
$var wire 4 ! Q [3:0] $end
$var reg 1 " clk $end
$var reg 1 # reset $end
$scope module c1 $end
$var wire 1 " clk $end
$var wire 1 # reset $end
$var reg 4 $ Q [3:0] $end
$upscope $end
$upscope $end
$enddefinitions $end
#0
$dumpvars
b0 $
0#
0"
b0 !
$end
#500
b1 !
b1 $
1"
#1000
0"
#1500
b10 !
b10 $
1"
#2000
0"
#2500
b11 !
b11 $
1"
#3000
0"
#3500
b100 !
b100 $
1"
#4000
0"
#4500
b101 !
b101 $
1"
#5000
0"
#5500
b110 !
b110 $
1"
#6000
0"
#6500
b111 !
b111 $
1"
#7000
0"
#7500
b1000 !
b1000 $
1"
#8000
0"
#8500
b1001 !
b1001 $
1"
#9000
0"
#9500
b1010 !
b1010 $
1"
#10000
0"
1#
#10500
b0 !
b0 $
1"
#11000
0"
0#
#11500
b1 !
b1 $
1"
#12000
0"
#12500
b10 !
b10 $
1"
#13000
0"
#13500
b11 !
b11 $
1"
#14000
0"
#14500
b100 !
b100 $
1"
#15000
0"
#15500
b101 !
b101 $
1"
#16000
0"
#16500
b110 !
b110 $
1"
#17000
0"
#17500
b111 !
b111 $
1"
#18000
0"
#18500
b1000 !
b1000 $
1"
#19000
0"
#19500
b1001 !
b1001 $
1"
#20000
0"
#20500
b1010 !
b1010 $
1"
#21000
0"
#21500
b1011 !
b1011 $
1"
#22000
0"
#22500
b1100 !
b1100 $
1"
#23000
0"
#23500
b1101 !
b1101 $
1"
#24000
0"
#24500
b1110 !
b1110 $
1"
#25000
0"
#25500
b1111 !
b1111 $
1"
#26000
0"
#26500
b0 !
b0 $
1"
#27000
0"
#27500
b1 !
b1 $
1"
#28000
0"
#28500
b10 !
b10 $
1"
#29000
0"
#29500
b11 !
b11 $
1"
#30000
0"
#30500
b100 !
b100 $
1"
#31000
0"
#31500
b101 !
b101 $
1"
#32000
0"
#32500
b110 !
b110 $
1"
#33000
0"
#33500
b111 !
b111 $
1"
#34000
0"
#34500
b1000 !
b1000 $
1"
#35000
0"
#35500
b1001 !
b1001 $
1"
#36000
0"
#36500
b1010 !
b1010 $
1"
#37000
0"
#37500
b1011 !
b1011 $
1"
#38000
0"
#38500
b1100 !
b1100 $
1"
#39000
0"
#39500
b1101 !
b1101 $
1"
#40000
0"
#40500
b1110 !
b1110 $
1"
#41000
0"
#41500
b1111 !
b1111 $
1"
#42000
0"
#42500
b0 !
b0 $
1"
#43000
0"
#43500
b1 !
b1 $
1"
#44000
0"
#44500
b10 !
b10 $
1"
#45000
0"
#45500
b11 !
b11 $
1"
#46000
0"
#46500
b100 !
b100 $
1"
#47000
0"
#47500
b101 !
b101 $
1"
#48000
0"
#48500
b110 !
b110 $
1"
#49000
0"
#49500
b111 !
b111 $
1"
#50000
0"
#50500
b1000 !
b1000 $
1"
#51000
0"
#51500
b1001 !
b1001 $
1"
#52000
0"
#52500
b1010 !
b1010 $
1"
#53000
0"
#53500
b1011 !
b1011 $
1"
#54000
0"
#54500
b1100 !
b1100 $
1"
#55000
0"
#55500
b1101 !
b1101 $
1"
#56000
0"
#56500
b1110 !
b1110 $
1"
#57000
0"
#57500
b1111 !
b1111 $
1"
#58000
0"
#58500
b0 !
b0 $
1"
#59000
0"
#59500
b1 !
b1 $
1"
#60000
0"
#60500
b10 !
b10 $
1"
#61000
0"
1#
#61500
b0 !
b0 $
1"
#62000
0"
0#
#62500
b1 !
b1 $
1"
#63000
0"
#63500
b10 !
b10 $
1"
#64000
0"
#64500
b11 !
b11 $
1"
#65000
0"
#65500
b100 !
b100 $
1"
#66000
0"
#66500
b101 !
b101 $
1"
#67000
0"
#67500
b110 !
b110 $
1"
#68000
0"
#68500
b111 !
b111 $
1"
#69000
0"
#69500
b1000 !
b1000 $
1"
#70000
0"
#70500
b1001 !
b1001 $
1"
#71000
0"
#71500
b1010 !
b1010 $
1"
#72000
0"
#72500
b1011 !
b1011 $
1"
#73000
0"
#73500
b1100 !
b1100 $
1"
#74000
0"
#74500
b1101 !
b1101 $
1"
#75000
0"
#75500
b1110 !
b1110 $
1"
#76000
0"
#76500
b1111 !
b1111 $
1"
#77000
0"
#77500
b0 !
b0 $
1"
#78000
0"
#78500
b1 !
b1 $
1"
#79000
0"
#79500
b10 !
b10 $
1"
#80000
0"
#80500
b11 !
b11 $
1"
#81000
0"
#81500
b100 !
b100 $
1"
#82000
0"
#82500
b101 !
b101 $
1"
#83000
0"
#83500
b110 !
b110 $
1"
#84000
0"
#84500
b111 !
b111 $
1"
#85000
0"
#85500
b1000 !
b1000 $
1"
#86000
0"
#86500
b1001 !
b1001 $
1"
#87000
0"
#87500
b1010 !
b1010 $
1"
#88000
0"
#88500
b1011 !
b1011 $
1"
#89000
0"
#89500
b1100 !
b1100 $
1"
#90000
0"
#90500
b1101 !
b1101 $
1"
#91000
0"
#91500
b1110 !
b1110 $
1"
#92000
0"
#92500
b1111 !
b1111 $
1"
#93000
0"
#93500
b0 !
b0 $
1"
#94000
0"
#94500
b1 !
b1 $
1"
#95000
0"
#95500
b10 !
b10 $
1"
#96000
0"
#96500
b11 !
b11 $
1"
#97000
0"
#97500
b100 !
b100 $
1"
#98000
0"
#98500
b101 !
b101 $
1"
#99000
0"
#99500
b110 !
b110 $
1"
#100000
0"
#100500
b111 !
b111 $
1"
#101000
0"
#101500
b1000 !
b1000 $
1"
#102000
0"
#102500
b1001 !
b1001 $
1"
#103000
0"
#103500
b1010 !
b1010 $
1"
#104000
0"
#104500
b1011 !
b1011 $
1"
#105000
0"
#105500
b1100 !
b1100 $
1"
#106000
0"
#106500
b1101 !
b1101 $
1"
#107000
0"
#107500
b1110 !
b1110 $
1"
#108000
0"
#108500
b1111 !
b1111 $
1"
#109000
0"
#109500
b0 !
b0 $
1"
#110000
0"
#110500
b1 !
b1 $
1"
#111000
0"
#111500
b10 !
b10 $
1"
#112000
0"
#112500
b11 !
b11 $
1"
#113000
0"
#113500
b100 !
b100 $
1"
#114000
0"
#114500
b101 !
b101 $
1"
#115000
0"
#115500
b110 !
b110 $
1"
#116000
0"
#116500
b111 !
b111 $
1"
#117000
0"
#117500
b1000 !
b1000 $
1"
#118000
0"
#118500
b1001 !
b1001 $
1"
#119000
0"
#119500
b1010 !
b1010 $
1"
#120000
0"
#120500
b1011 !
b1011 $
1"
#121000
0"
#121500
b1100 !
b1100 $
1"
#122000
0"
#122500
b1101 !
b1101 $
1"
#123000
0"
#123500
b1110 !
b1110 $
1"
#124000
0"
#124500
b1111 !
b1111 $
1"
#125000
0"
#125500
b0 !
b0 $
1"
#126000
0"
#126500
b1 !
b1 $
1"
#127000
0"
#127500
b10 !
b10 $
1"
#128000
0"
#128500
b11 !
b11 $
1"
#129000
0"
#129500
b100 !
b100 $
1"
#130000
0"
#130500
b101 !
b101 $
1"
#131000
0"
#131500
b110 !
b110 $
1"
#132000
0"
#132500
b111 !
b111 $
1"
#133000
0"
#133500
b1000 !
b1000 $
1"
#134000
0"
#134500
b1001 !
b1001 $
1"
#135000
0"
#135500
b1010 !
b1010 $
1"
#136000
0"
#136500
b1011 !
b1011 $
1"
#137000
0"
#137500
b1100 !
b1100 $
1"
#138000
0"
#138500
b1101 !
b1101 $
1"
#139000
0"
#139500
b1110 !
b1110 $
1"
#140000
0"
#140500
b1111 !
b1111 $
1"
#141000
0"
#141500
b0 !
b0 $
1"
#142000
0"
#142500
b1 !
b1 $
1"
#143000
0"
#143500
b10 !
b10 $
1"
#144000
0"
#144500
b11 !
b11 $
1"
#145000
0"
#145500
b100 !
b100 $
1"
#146000
0"
#146500
b101 !
b101 $
1"
#147000
0"
#147500
b110 !
b110 $
1"
#148000
0"
#148500
b111 !
b111 $
1"
#149000
0"
#149500
b1000 !
b1000 $
1"
#150000
0"
#150500
b1001 !
b1001 $
1"
#151000
0"
#151500
b1010 !
b1010 $
1"
#152000
0"
#152500
b1011 !
b1011 $
1"
#153000
0"
#153500
b1100 !
b1100 $
1"
#154000
0"
#154500
b1101 !
b1101 $
1"
#155000
0"
#155500
b1110 !
b1110 $
1"
#156000
0"
#156500
b1111 !
b1111 $
1"
#157000
0"
#157500
b0 !
b0 $
1"
#158000
0"
#158500
b1 !
b1 $
1"
#159000
0"
#159500
b10 !
b10 $
1"
#160000
0"
#160500
b11 !
b11 $
1"
#161000
0"
#161500
b100 !
b100 $
1"
