Verilog/0101 Seq_detector/seq_det.v
`timescale 1ns/1ps
module seq_det(din, reset, clk, z);
	input clk, reset, din;
	output reg z;
	reg [1:0] cst, nst;
	parameter A=2'b00, B=2'b01, C=2'b10, D=2'b11;

	always @(cst or din)
	begin
		case(cst)
		A: if(din == 1'b0) begin
			nst = B; z = 1'b0; end
		   else begin
			nst = A; z = 1'b0; end

		B: if(din == 1'b1) begin
			nst = C; z = 1'b0; end
		   else begin
			nst = B; z = 1'b0; end

		C: if(din == 1'b0) begin
			nst = D; z = 1'b0; end
		   else begin
			nst = A; z = 1'b0; end

		D: if(din == 1'b1) begin 
			nst = C; z = 1'b1; end
		   else begin
			nst = B; z = 1'b0; end
		default: nst = A;
		endcase
	end
	
	always @(posedge(clk))
	begin 
		if(reset)
			cst <= A;
		else 
			cst <= nst;
	end 
	endmodule

Verilog/0101 Seq_detector/module seq_det_tb.v
`timescale 1ns/1ps
`include "seq_det.v"
module seq_det_tb;
reg din, clk, reset;
wire z;
seq_det m1(din, reset, clk, z);
initial
begin
reset=0;clk=0;din=0;

$monitor($time, , ,"c=%b",clk,,"z=%b",z,,"r=%b",reset,,"d=%b",din);
$dumpfile("seq_det.vcd");
$dumpvars;
#10 din<=1;
#10 din<=1;
#10 din<=1;
#10 din<=1;
#10 din<=1;
#10 din<=0;
#10 din<=1;
#10 din<=0;
#10 din<=1;
#10 din<=0;
#10 din<=1;
#10 din<=1;
#10 din<=1;
#10 din<=1;
#10 din<=1;
#10 din<=1;
#10 din<=0;
#10 din<=1;
#10 din<=0;
#10 din<=1;
#10 din<=0;
#10 din<=1;
//#5 reset=1;
//#5 reset=0;
end

always
#5 clk=~clk;
initial
#1000 $finish ;
endmodule

Verilog/0101 Seq_detector/seq_det.vcd
$date
	Sat Oct 21 23:32:35 2017
$end
$version
	Icarus Verilog
$end
$timescale
	1ps
$end
$scope module seq_det_tb $end
$var wire 1 ! z $end
$var reg 1 " clk $end
$var reg 1 # din $end
$var reg 1 $ reset $end
$scope module m1 $end
$var wire 1 " clk $end
$var wire 1 # din $end
$var wire 1 $ reset $end
$var reg 2 % cst [1:0] $end
$var reg 2 & nst [1:0] $end
$var reg 1 ! z $end
$upscope $end
$upscope $end
$enddefinitions $end
#0
$dumpvars
b0 &
bx %
0$
0#
0"
x!
$end
#5000
0!
b1 &
b0 %
1"
#10000
b0 &
1#
0"
#15000
1"
#20000
0"
#25000
1"
#30000
0"
#35000
1"
#40000
0"
#45000
1"
#50000
0"
#55000
1"
#60000
b1 &
0#
0"
#65000
b1 %
1"
#70000
b10 &
1#
0"
#75000
b0 &
b10 %
1"
#80000
b11 &
0#
0"
#85000
b1 &
b11 %
1"
#90000
1!
b10 &
1#
0"
#95000
0!
b0 &
b10 %
1"
#100000
b11 &
0#
0"
#105000
b1 &
b11 %
1"
#110000
1!
b10 &
1#
0"
#115000
0!
b0 &
b10 %
1"
#120000
0"
#125000
b0 %
1"
#130000
0"
#135000
1"
#140000
0"
#145000
1"
#150000
0"
#155000
1"
#160000
0"
#165000
1"
#170000
b1 &
0#
0"
#175000
b1 %
1"
#180000
b10 &
1#
0"
#185000
b0 &
b10 %
1"
#190000
b11 &
0#
0"
#195000
b1 &
b11 %
1"
#200000
1!
b10 &
1#
0"
#205000
0!
b0 &
b10 %
1"
#210000
b11 &
0#
0"
#215000
b1 &
b11 %
1"
#220000
1!
b10 &
1#
0"
#225000
0!
b0 &
b10 %
1"
#230000
0"
#235000
b0 %
1"
