4_Bit_Binary_Counter/counter.v
module counter(clk,reset,Q);

input clk;
output[3:0] Q;
input reset;

wire clk,reset;
reg[3:0] Q;


initial Q=0;

always @ (posedge(clk)) 
	begin
		if (reset)
		
			Q<=0;
		
		else 
		
			
			Q <=Q+1;
			
			
	end
endmodule

4_Bit_Binary_Counter/counter_tb.v
`timescale 1ns/100ps
`include "counter.v"

module Top;
reg clk;
reg reset;
wire[3:0] Q;

counter c1(clk, reset , Q);
 

initial 
	begin
		reset = 0;
		
		#10000 $finish;

	end

always 
	begin

		clk = 0; #50;
		clk = 1; #50;
	end

initial
begin
	

 $monitor($stime," clk = %b, reset = %b, dout = %h",clk,reset,Q );
$dumpfile("counter.vcd");
$dumpvars;

end
endmodule

4_Bit_Binary_Counter/counter.vcd
$date
	Wed Oct 11 21:14:04 2017
$end
$version
	Icarus Verilog
$end
$timescale
	100ps
$end
$scope module Top $end
$var wire 4 ! Q [3:0] $end
$var reg 1 " clk $end
$var reg 1 # reset $end
$scope module c1 $end
$var wire 1 " clk $end
$var wire 1 # reset $end
$var reg 4 $ Q [3:0] $end
$upscope $end
$upscope $end
$enddefinitions $end
#0
$dumpvars
b0 $
0#
0"
b0 !
$end
#500
b1 !
b1 $
1"
#1000
0"
#1500
b10 !
b10 $
1"
#2000
0"
#2500
b11 !
b11 $
1"
#3000
0"
#3500
b100 !
b100 $
1"
#4000
0"
#4500
b101 !
b101 $
1"
#5000
0"
#5500
b110 !
b110 $
1"
#6000
0"
#6500
b111 !
b111 $
1"
#7000
0"
#7500
b1000 !
b1000 $
1"
#8000
0"
#8500
b1001 !
b1001 $
1"
#9000
0"
#9500
b1010 !
b1010 $
1"
#10000
0"
#10500
b1011 !
b1011 $
1"
#11000
0"
#11500
b1100 !
b1100 $
1"
#12000
0"
#12500
b1101 !
b1101 $
1"
#13000
0"
#13500
b1110 !
b1110 $
1"
#14000
0"
#14500
b1111 !
b1111 $
1"
#15000
0"
#15500
b0 !
b0 $
1"
#16000
0"
#16500
b1 !
b1 $
1"
#17000
0"
#17500
b10 !
b10 $
1"
#18000
0"
#18500
b11 !
b11 $
1"
#19000
0"
#19500
b100 !
b100 $
1"
#20000
0"
#20500
b101 !
b101 $
1"
#21000
0"
#21500
b110 !
b110 $
1"
#22000
0"
#22500
b111 !
b111 $
1"
#23000
0"
#23500
b1000 !
b1000 $
1"
#24000
0"
#24500
b1001 !
b1001 $
1"
#25000
0"
#25500
b1010 !
b1010 $
1"
#26000
0"
#26500
b1011 !
b1011 $
1"
#27000
0"
#27500
b1100 !
b1100 $
1"
#28000
0"
#28500
b1101 !
b1101 $
1"
#29000
0"
#29500
b1110 !
b1110 $
1"
#30000
0"
#30500
b1111 !
b1111 $
1"
#31000
0"
#31500
b0 !
b0 $
1"
#32000
0"
#32500
b1 !
b1 $
1"
#33000
0"
#33500
b10 !
b10 $
1"
#34000
0"
#34500
b11 !
b11 $
1"
#35000
0"
#35500
b100 !
b100 $
1"
#36000
0"
#36500
b101 !
b101 $
1"
#37000
0"
#37500
b110 !
b110 $
1"
#38000
0"
#38500
b111 !
b111 $
1"
#39000
0"
#39500
b1000 !
b1000 $
1"
#40000
0"
#40500
b1001 !
b1001 $
1"
#41000
0"
#41500
b1010 !
b1010 $
1"
#42000
0"
#42500
b1011 !
b1011 $
1"
#43000
0"
#43500
b1100 !
b1100 $
1"
#44000
0"
#44500
b1101 !
b1101 $
1"
#45000
0"
#45500
b1110 !
b1110 $
1"
#46000
0"
#46500
b1111 !
b1111 $
1"
#47000
0"
#47500
b0 !
b0 $
1"
#48000
0"
#48500
b1 !
b1 $
1"
#49000
0"
#49500
b10 !
b10 $
1"
#50000
0"
#50500
b11 !
b11 $
1"
#51000
0"
#51500
b100 !
b100 $
1"
#52000
0"
#52500
b101 !
b101 $
1"
#53000
0"
#53500
b110 !
b110 $
1"
#54000
0"
#54500
b111 !
b111 $
1"
#55000
0"
#55500
b1000 !
b1000 $
1"
#56000
0"
#56500
b1001 !
b1001 $
1"
#57000
0"
#57500
b1010 !
b1010 $
1"
#58000
0"
#58500
b1011 !
b1011 $
1"
#59000
0"
#59500
b1100 !
b1100 $
1"
#60000
0"
#60500
b1101 !
b1101 $
1"
#61000
0"
#61500
b1110 !
b1110 $
1"
#62000
0"
#62500
b1111 !
b1111 $
1"
#63000
0"
#63500
b0 !
b0 $
1"
#64000
0"
#64500
b1 !
b1 $
1"
#65000
0"
#65500
b10 !
b10 $
1"
#66000
0"
#66500
b11 !
b11 $
1"
#67000
0"
#67500
b100 !
b100 $
1"
#68000
0"
#68500
b101 !
b101 $
1"
#69000
0"
#69500
b110 !
b110 $
1"
#70000
0"
#70500
b111 !
b111 $
1"
#71000
0"
#71500
b1000 !
b1000 $
1"
#72000
0"
#72500
b1001 !
b1001 $
1"
#73000
0"
#73500
b1010 !
b1010 $
1"
#74000
0"
#74500
b1011 !
b1011 $
1"
#75000
0"
#75500
b1100 !
b1100 $
1"
#76000
0"
#76500
b1101 !
b1101 $
1"
#77000
0"
#77500
b1110 !
b1110 $
1"
#78000
0"
#78500
b1111 !
b1111 $
1"
#79000
0"
#79500
b0 !
b0 $
1"
#80000
0"
#80500
b1 !
b1 $
1"
#81000
0"
#81500
b10 !
b10 $
1"
#82000
0"
#82500
b11 !
b11 $
1"
#83000
0"
#83500
b100 !
b100 $
1"
#84000
0"
#84500
b101 !
b101 $
1"
#85000
0"
#85500
b110 !
b110 $
1"
#86000
0"
#86500
b111 !
b111 $
1"
#87000
0"
#87500
b1000 !
b1000 $
1"
#88000
0"
#88500
b1001 !
b1001 $
1"
#89000
0"
#89500
b1010 !
b1010 $
1"
#90000
0"
#90500
b1011 !
b1011 $
1"
#91000
0"
#91500
b1100 !
b1100 $
1"
#92000
0"
#92500
b1101 !
b1101 $
1"
#93000
0"
#93500
b1110 !
b1110 $
1"
#94000
0"
#94500
b1111 !
b1111 $
1"
#95000
0"
#95500
b0 !
b0 $
1"
#96000
0"
#96500
b1 !
b1 $
1"
#97000
0"
#97500
b10 !
b10 $
1"
#98000
0"
#98500
b11 !
b11 $
1"
#99000
0"
#99500
b100 !
b100 $
1"
