Verilog/full_adder/Behavioral/fulladder.v
module fulladder (sum, c_out, in0, in1, c_in);

output sum, c_out;
input in0, in1, c_in;

assign { c_out, sum } = in0 + in1 + c_in;

endmodule

Verilog/full_adder/Gate_level/fulladder_tb.v
`timescale 1ns/100ps
`include "fulladder.v"

module Top;

wire sum,c1;
reg a,b,c;

fulladder fu1(sum,c1,a,b,c);


initial 

begin
	$dumpfile("fulladder.vcd");
	$dumpvars;

	$monitor($time,"a=%b, b=%b , c=%b ,sum=%b, carry=%b\n",a,b,c,sum,c1);
	a=0;b=0;c=0;
	#5 a=0;b=0;c=1;
	#5 a=0;b=1;c=0;
	#5 a=0;b=1;c=1;
	#5 a=1;b=0;c=0;
	#5 a=1;b=0;c=1;
	#5 a=1;b=1;c=0;
	#5 a=1;b=1;c=1;
	#5 a=0;b=0;c=0;
	#5;



end

endmodule

Verilog/full_adder/Behavioral/fulladder.vcd
$date
	Sun Oct  1 16:26:53 2017
$end
$version
	Icarus Verilog
$end
$timescale
	100ps
$end
$scope module Top $end
$var wire 1 ! sum $end
$var wire 1 " c1 $end
$var reg 1 # a $end
$var reg 1 $ b $end
$var reg 1 % c $end
$scope module fu1 $end
$var wire 1 % c_in $end
$var wire 1 # in0 $end
$var wire 1 $ in1 $end
$var wire 1 ! sum $end
$var wire 1 " c_out $end
$upscope $end
$upscope $end
$enddefinitions $end
#0
$dumpvars
0%
0$
0#
0"
0!
$end
#50
1!
1%
#100
0%
1$
#150
0!
1"
1%
#200
0"
1!
0%
0$
1#
#250
0!
1"
1%
#300
0%
1$
#350
1!
1%
#400
0"
0!
0%
0$
0#
